rtandcaskinetics-0.2.0.dist-info/METADATA
rtandcaskinetics-0.2.0.dist-info/WHEEL
rtandcaskinetics-0.2.0.dist-info/entry_points.txt
rtandcaskinetics-0.2.0.dist-info/licenses/LICENSE
rtandcaskinetics/.DS_Store
rtandcaskinetics/__init__.py
rtandcaskinetics/casmodel.py
rtandcaskinetics/casmodel_func.py
rtandcaskinetics/probability_func.py
rtandcaskinetics-0.2.0.dist-info/RECORD
