Metadata-Version: 2.1
Name: RTandCasKinetics
Version: 0.2.0
Summary: Model that investigates the combined kinetics of HIV reverse transcriptase and CRISPR Cas12a.
Author-Email: Maya Singh <msingh6@uw.edu>
License: MIT
Project-URL: Homepage, https://github.com/msingh0606/RTandCasKinetics
Requires-Python: >=3.9
Requires-Dist: numpy>=1.24.0
Requires-Dist: matplotlib>=3.9.3
Requires-Dist: tellurium>=2.2.10
Requires-Dist: pytest>=8.3.4
Requires-Dist: pyqt5>=5.15.11
Requires-Dist: pip>=24.3.1
